arbiterx/__init__.py
arbiterx/exceptions.py
arbiterx/logger.py
arbiterx/main.py
arbiterx/types.py
arbiterx/verdicts.py
arbiterx-0.2.5.dist-info/METADATA
arbiterx-0.2.5.dist-info/WHEEL
arbiterx-0.2.5.dist-info/RECORD
