Metadata-Version: 2.3
Name: arbiterx
Version: 0.2.5
Summary: 
Author: parthokr
Author-email: partho.kr@proton.me
Requires-Python: >=3.13
Classifier: Programming Language :: Python :: 3
Classifier: Programming Language :: Python :: 3.13
Requires-Dist: rich (>=13.9.4,<14.0.0)
